bluetooth_mesh/messages/__init__.py
bluetooth_mesh/messages/config.py
bluetooth_mesh/messages/generics.py
bluetooth_mesh/messages/health.py
bluetooth_mesh/messages/properties.py
bluetooth_mesh/messages/scene.py
bluetooth_mesh/messages/sensor.py
bluetooth_mesh/messages/time.py
bluetooth_mesh/messages/util.py
bluetooth_mesh/messages/capnproto/__init__.py
bluetooth_mesh/messages/capnproto/generator.py
bluetooth_mesh/messages/generic/__init__.py
bluetooth_mesh/messages/generic/battery.py
bluetooth_mesh/messages/generic/level.py
bluetooth_mesh/messages/generic/onoff.py
bluetooth_mesh/messages/generic/property.py
bluetooth_mesh/messages/light/__init__.py
bluetooth_mesh/messages/light/ctl.py
bluetooth_mesh/messages/light/lightness.py
bluetooth_mesh/messages/silvair/__init__.py
bluetooth_mesh/messages/silvair/debug.py
bluetooth_mesh/messages/silvair/debugV2.py
bluetooth_mesh/messages/silvair/emergency_lighting.py
bluetooth_mesh/messages/silvair/emergency_lighting_test.py
bluetooth_mesh/messages/silvair/gateway_config_server.py
bluetooth_mesh/messages/silvair/light_extended_controller.py
bluetooth_mesh/messages/silvair/network_diagnostic_server.py
bluetooth_mesh/messages/silvair/rrule_scheduler.py
bluetooth_mesh_messages-0.9.12.dist-info/licenses/LICENSE
bluetooth_mesh_messages-0.9.12.dist-info/METADATA
bluetooth_mesh_messages-0.9.12.dist-info/WHEEL
bluetooth_mesh_messages-0.9.12.dist-info/top_level.txt
bluetooth_mesh_messages-0.9.12.dist-info/RECORD
